{
  "bioguide_id": "H001090",
  "congress": 119,
  "kind": "sponsored",
  "generated_at": "2026-05-07T20:15:59Z",
  "bills": [
    {
      "id": "hr8572-119",
      "type": "hr",
      "number": "8572",
      "congress": 119,
      "title": "Gas Prices Relief Act of 2026",
      "introduced_date": "2026-04-29",
      "latest_action": {
        "date": "2026-04-29",
        "text": "Referred to the House Committee on Ways and Means."
      },
      "policy_area": null
    },
    {
      "id": "hr7791-119",
      "type": "hr",
      "number": "7791",
      "congress": 119,
      "title": "To authorize the Secretary of Housing and Urban Development to prioritize the award of certain housing grants to applicants located in, or serving, low-income communities.",
      "introduced_date": "2026-03-04",
      "latest_action": {
        "date": "2026-03-04",
        "text": "Referred to the House Committee on Financial Services."
      },
      "policy_area": "Housing and Community Development"
    },
    {
      "id": "hr7496-119",
      "type": "hr",
      "number": "7496",
      "congress": 119,
      "title": "Health Investment Zones Act of 2026",
      "introduced_date": "2026-02-11",
      "latest_action": {
        "date": "2026-02-11",
        "text": "Referred to the Committee on Energy and Commerce, and in addition to the Committees on Ways and Means, and Education and Workforce, for a period to be subsequently determined by the Speaker, in each case for consideration of such provisions as fall within the jurisdiction of the committee concerned."
      },
      "policy_area": "Taxation"
    },
    {
      "id": "hr7329-119",
      "type": "hr",
      "number": "7329",
      "congress": 119,
      "title": "FREEDOM Act",
      "introduced_date": "2026-02-03",
      "latest_action": {
        "date": "2026-02-03",
        "text": "Referred to the Committee on Natural Resources, and in addition to the Committees on Agriculture, Energy and Commerce, Transportation and Infrastructure, Science, Space, and Technology, and the Judiciary, for a period to be subsequently determined by the Speaker, in each case for consideration of such provisions as fall within the jurisdiction of the committee concerned."
      },
      "policy_area": "Energy"
    },
    {
      "id": "hr7214-119",
      "type": "hr",
      "number": "7214",
      "congress": 119,
      "title": "End PG&E Lobbying Act",
      "introduced_date": "2026-01-22",
      "latest_action": {
        "date": "2026-01-22",
        "text": "Referred to the House Committee on Energy and Commerce."
      },
      "policy_area": "Energy"
    },
    {
      "id": "hr7215-119",
      "type": "hr",
      "number": "7215",
      "congress": 119,
      "title": "Stop SCAMS Act",
      "introduced_date": "2026-01-22",
      "latest_action": {
        "date": "2026-01-22",
        "text": "Referred to the Committee on the Judiciary, and in addition to the Committees on Energy and Commerce, and Financial Services, for a period to be subsequently determined by the Speaker, in each case for consideration of such provisions as fall within the jurisdiction of the committee concerned."
      },
      "policy_area": "Finance and Financial Sector"
    },
    {
      "id": "hr6863-119",
      "type": "hr",
      "number": "6863",
      "congress": 119,
      "title": "CAT Act of 2025",
      "introduced_date": "2025-12-18",
      "latest_action": {
        "date": "2025-12-18",
        "text": "Referred to the Committee on Energy and Commerce, and in addition to the Committee on Ways and Means, for a period to be subsequently determined by the Speaker, in each case for consideration of such provisions as fall within the jurisdiction of the committee concerned."
      },
      "policy_area": "Health"
    },
    {
      "id": "hr6862-119",
      "type": "hr",
      "number": "6862",
      "congress": 119,
      "title": "Protecting Health Care Workforce Pipelines Act",
      "introduced_date": "2025-12-18",
      "latest_action": {
        "date": "2025-12-18",
        "text": "Referred to the House Committee on Education and Workforce."
      },
      "policy_area": "Education"
    },
    {
      "id": "hr6747-119",
      "type": "hr",
      "number": "6747",
      "congress": 119,
      "title": "Olive Oil Standards Act",
      "introduced_date": "2025-12-16",
      "latest_action": {
        "date": "2025-12-16",
        "text": "Referred to the House Committee on Energy and Commerce."
      },
      "policy_area": "Health"
    },
    {
      "id": "hr6572-119",
      "type": "hr",
      "number": "6572",
      "congress": 119,
      "title": "Launching X–Labs for Breakthrough Science Act",
      "introduced_date": "2025-12-10",
      "latest_action": {
        "date": "2025-12-10",
        "text": "Referred to the House Committee on Energy and Commerce."
      },
      "policy_area": "Health"
    },
    {
      "id": "hr6523-119",
      "type": "hr",
      "number": "6523",
      "congress": 119,
      "title": "To direct the United States Postal Service to establish a post office in Mountain House, California.",
      "introduced_date": "2025-12-09",
      "latest_action": {
        "date": "2025-12-09",
        "text": "Referred to the House Committee on Oversight and Government Reform."
      },
      "policy_area": "Government Operations and Politics"
    },
    {
      "id": "hr6008-119",
      "type": "hr",
      "number": "6008",
      "congress": 119,
      "title": "Bring Down Housing Costs Act",
      "introduced_date": "2025-11-10",
      "latest_action": {
        "date": "2025-11-10",
        "text": "Referred to the House Committee on Financial Services."
      },
      "policy_area": "Housing and Community Development"
    },
    {
      "id": "hr5881-119",
      "type": "hr",
      "number": "5881",
      "congress": 119,
      "title": "Double Dependents Relief Act",
      "introduced_date": "2025-10-31",
      "latest_action": {
        "date": "2025-10-31",
        "text": "Referred to the House Committee on Ways and Means."
      },
      "policy_area": "Taxation"
    },
    {
      "id": "hr5751-119",
      "type": "hr",
      "number": "5751",
      "congress": 119,
      "title": "CPUC Act",
      "introduced_date": "2025-10-14",
      "latest_action": {
        "date": "2025-10-14",
        "text": "Referred to the House Committee on Energy and Commerce."
      },
      "policy_area": "Energy"
    },
    {
      "id": "hr5550-119",
      "type": "hr",
      "number": "5550",
      "congress": 119,
      "title": "Lower Internet Costs Act",
      "introduced_date": "2025-09-23",
      "latest_action": {
        "date": "2025-09-23",
        "text": "Referred to the House Committee on Energy and Commerce."
      },
      "policy_area": "Science, Technology, Communications"
    },
    {
      "id": "hr5359-119",
      "type": "hr",
      "number": "5359",
      "congress": 119,
      "title": "No Bribes for Politicians Act of 2025",
      "introduced_date": "2025-09-15",
      "latest_action": {
        "date": "2025-09-15",
        "text": "Referred to the House Committee on Oversight and Government Reform."
      },
      "policy_area": "Government Operations and Politics"
    },
    {
      "id": "hr5141-119",
      "type": "hr",
      "number": "5141",
      "congress": 119,
      "title": "Stop the Rate Hikes Act",
      "introduced_date": "2025-09-04",
      "latest_action": {
        "date": "2025-09-04",
        "text": "Referred to the House Committee on Energy and Commerce."
      },
      "policy_area": "Energy"
    },
    {
      "id": "hr4949-119",
      "type": "hr",
      "number": "4949",
      "congress": 119,
      "title": "Apprenticeships for Small Businesses Act of 2025",
      "introduced_date": "2025-08-12",
      "latest_action": {
        "date": "2025-08-12",
        "text": "Referred to the House Committee on Ways and Means."
      },
      "policy_area": "Taxation"
    },
    {
      "id": "hr4852-119",
      "type": "hr",
      "number": "4852",
      "congress": 119,
      "title": "Wildfire Emergency Preparedness Act of 2025",
      "introduced_date": "2025-08-01",
      "latest_action": {
        "date": "2025-08-02",
        "text": "Referred to the Subcommittee on Economic Development, Public Buildings, and Emergency Management."
      },
      "policy_area": "Emergency Management"
    },
    {
      "id": "hr4799-119",
      "type": "hr",
      "number": "4799",
      "congress": 119,
      "title": "Ban Corporate PACs Act",
      "introduced_date": "2025-07-29",
      "latest_action": {
        "date": "2025-07-29",
        "text": "Referred to the House Committee on House Administration."
      },
      "policy_area": "Government Operations and Politics"
    },
    {
      "id": "hr4671-119",
      "type": "hr",
      "number": "4671",
      "congress": 119,
      "title": "Ensuring Casualty Assistance for our Firefighters Act",
      "introduced_date": "2025-07-23",
      "latest_action": {
        "date": "2026-02-11",
        "text": "Ordered to be Reported by Unanimous Consent."
      },
      "policy_area": "Emergency Management"
    },
    {
      "id": "hr4672-119",
      "type": "hr",
      "number": "4672",
      "congress": 119,
      "title": "To extend the break-in-service consideration for firefighter retirements, and other purposes.",
      "introduced_date": "2025-07-23",
      "latest_action": {
        "date": "2025-07-23",
        "text": "Referred to the House Committee on Oversight and Government Reform."
      },
      "policy_area": "Government Operations and Politics"
    },
    {
      "id": "hr4079-119",
      "type": "hr",
      "number": "4079",
      "congress": 119,
      "title": "Safer Response Act of 2025",
      "introduced_date": "2025-06-23",
      "latest_action": {
        "date": "2025-06-23",
        "text": "Referred to the House Committee on Energy and Commerce."
      },
      "policy_area": "Health"
    },
    {
      "id": "hr3846-119",
      "type": "hr",
      "number": "3846",
      "congress": 119,
      "title": "Retired Law Enforcement Officers Continuing Service Act",
      "introduced_date": "2025-06-09",
      "latest_action": {
        "date": "2025-06-09",
        "text": "Referred to the House Committee on the Judiciary."
      },
      "policy_area": "Crime and Law Enforcement"
    },
    {
      "id": "hr3768-119",
      "type": "hr",
      "number": "3768",
      "congress": 119,
      "title": "Gas Prices Relief Act of 2025",
      "introduced_date": "2025-06-05",
      "latest_action": {
        "date": "2025-06-05",
        "text": "Referred to the House Committee on Ways and Means."
      },
      "policy_area": "Taxation"
    },
    {
      "id": "hr3717-119",
      "type": "hr",
      "number": "3717",
      "congress": 119,
      "title": "Golden Mussel Eradication and Control Act of 2025",
      "introduced_date": "2025-06-04",
      "latest_action": {
        "date": "2025-06-04",
        "text": "Referred to the Committee on Transportation and Infrastructure, and in addition to the Committee on Natural Resources, for a period to be subsequently determined by the Speaker, in each case for consideration of such provisions as fall within the jurisdiction of the committee concerned."
      },
      "policy_area": "Public Lands and Natural Resources"
    },
    {
      "id": "hr2910-119",
      "type": "hr",
      "number": "2910",
      "congress": 119,
      "title": "Youth Workforce Readiness Act of 2025",
      "introduced_date": "2025-04-14",
      "latest_action": {
        "date": "2025-04-14",
        "text": "Referred to the House Committee on Education and Workforce."
      },
      "policy_area": "Labor and Employment"
    },
    {
      "id": "hr2774-119",
      "type": "hr",
      "number": "2774",
      "congress": 119,
      "title": "Safeguarding Our Levees Act",
      "introduced_date": "2025-04-09",
      "latest_action": {
        "date": "2025-04-09",
        "text": "Referred to the Subcommittee on Water Resources and Environment."
      },
      "policy_area": "Water Resources Development"
    },
    {
      "id": "hr2500-119",
      "type": "hr",
      "number": "2500",
      "congress": 119,
      "title": "Abandoned Vessel Prevention Act",
      "introduced_date": "2025-03-31",
      "latest_action": {
        "date": "2025-03-31",
        "text": "Referred to the Subcommittee on Coast Guard and Maritime Transportation."
      },
      "policy_area": "Transportation and Public Works"
    },
    {
      "id": "hr2194-119",
      "type": "hr",
      "number": "2194",
      "congress": 119,
      "title": "Ending Drug Trafficking in Our Communities Act",
      "introduced_date": "2025-03-18",
      "latest_action": {
        "date": "2025-03-18",
        "text": "Referred to the Committee on Oversight and Government Reform, and in addition to the Committees on the Judiciary, and Energy and Commerce, for a period to be subsequently determined by the Speaker, in each case for consideration of such provisions as fall within the jurisdiction of the committee concerned."
      },
      "policy_area": "Crime and Law Enforcement"
    },
    {
      "id": "hr1923-119",
      "type": "hr",
      "number": "1923",
      "congress": 119,
      "title": "Modernizing Wildfire Safety and Prevention Act of 2025",
      "introduced_date": "2025-03-06",
      "latest_action": {
        "date": "2025-03-28",
        "text": "Referred to the Subcommittee on Forestry and Horticulture."
      },
      "policy_area": "Emergency Management"
    },
    {
      "id": "hr1694-119",
      "type": "hr",
      "number": "1694",
      "congress": 119,
      "title": "AI Accountability Act",
      "introduced_date": "2025-02-27",
      "latest_action": {
        "date": "2025-02-27",
        "text": "Referred to the House Committee on Energy and Commerce."
      },
      "policy_area": "Science, Technology, Communications"
    },
    {
      "id": "hr1311-119",
      "type": "hr",
      "number": "1311",
      "congress": 119,
      "title": "Stop the Delta Tunnel Act",
      "introduced_date": "2025-02-13",
      "latest_action": {
        "date": "2025-02-13",
        "text": "Referred to the Subcommittee on Water Resources and Environment."
      },
      "policy_area": "Environmental Protection"
    },
    {
      "id": "hr914-119",
      "type": "hr",
      "number": "914",
      "congress": 119,
      "title": "American CANS Act",
      "introduced_date": "2025-02-04",
      "latest_action": {
        "date": "2025-02-04",
        "text": "Referred to the House Committee on Ways and Means."
      },
      "policy_area": "Foreign Trade and International Finance"
    },
    {
      "id": "hr776-119",
      "type": "hr",
      "number": "776",
      "congress": 119,
      "title": "Nutria Eradication and Control Reauthorization Act of 2025",
      "introduced_date": "2025-01-28",
      "latest_action": {
        "date": "2025-02-05",
        "text": "Received in the Senate and Read twice and referred to the Committee on Environment and Public Works."
      },
      "policy_area": "Animals"
    },
    {
      "id": "hr581-119",
      "type": "hr",
      "number": "581",
      "congress": 119,
      "title": "Child Care Workforce and Facilities Act of 2025",
      "introduced_date": "2025-01-21",
      "latest_action": {
        "date": "2025-01-21",
        "text": "Referred to the House Committee on Education and Workforce."
      },
      "policy_area": "Families"
    },
    {
      "id": "hr345-119",
      "type": "hr",
      "number": "345",
      "congress": 119,
      "title": "Fire Department Repayment Act of 2025",
      "introduced_date": "2025-01-13",
      "latest_action": {
        "date": "2025-07-23",
        "text": "Ordered to be Reported (Amended) by Unanimous Consent."
      },
      "policy_area": "Public Lands and Natural Resources"
    },
    {
      "id": "hr10486-118",
      "type": "hr",
      "number": "10486",
      "congress": 118,
      "title": "Retired Law Enforcement Officers Continuing Service Act",
      "introduced_date": "2024-12-18",
      "latest_action": {
        "date": "2024-12-18",
        "text": "Referred to the House Committee on the Judiciary."
      },
      "policy_area": "Crime and Law Enforcement"
    },
    {
      "id": "hr10158-118",
      "type": "hr",
      "number": "10158",
      "congress": 118,
      "title": "To extend the break-in-service consideration for firefighter retirements, and other purposes.",
      "introduced_date": "2024-11-18",
      "latest_action": {
        "date": "2024-11-18",
        "text": "Referred to the House Committee on Oversight and Accountability."
      },
      "policy_area": "Government Operations and Politics"
    },
    {
      "id": "hr10142-118",
      "type": "hr",
      "number": "10142",
      "congress": 118,
      "title": "VA COMPETES Act",
      "introduced_date": "2024-11-15",
      "latest_action": {
        "date": "2024-11-20",
        "text": "Referred to the Subcommittee on Health."
      },
      "policy_area": "Armed Forces and National Security"
    },
    {
      "id": "hr10006-118",
      "type": "hr",
      "number": "10006",
      "congress": 118,
      "title": "CAT Act of 2024",
      "introduced_date": "2024-10-18",
      "latest_action": {
        "date": "2024-12-17",
        "text": "Referred to the Subcommittee on Health."
      },
      "policy_area": "Health"
    },
    {
      "id": "hr9899-118",
      "type": "hr",
      "number": "9899",
      "congress": 118,
      "title": "Abandoned Vessel Prevention Act",
      "introduced_date": "2024-10-01",
      "latest_action": {
        "date": "2024-10-02",
        "text": "Referred to the Subcommittee on Coast Guard and Maritime Transportation."
      },
      "policy_area": "Transportation and Public Works"
    },
    {
      "id": "-118",
      "type": "",
      "number": "",
      "congress": 118,
      "title": "",
      "introduced_date": "2024-09-24",
      "latest_action": {
        "date": "2024-09-24",
        "text": "On agreeing to the Harder (CA) amendment (A006) Agreed to by voice vote."
      },
      "policy_area": null
    },
    {
      "id": "hr9623-118",
      "type": "hr",
      "number": "9623",
      "congress": 118,
      "title": "Ending Drug Trafficking in Our Communities Act",
      "introduced_date": "2024-09-17",
      "latest_action": {
        "date": "2024-09-17",
        "text": "Referred to the Committee on Oversight and Accountability, and in addition to the Committees on the Judiciary, and Energy and Commerce, for a period to be subsequently determined by the Speaker, in each case for consideration of such provisions as fall within the jurisdiction of the committee concerned."
      },
      "policy_area": "Crime and Law Enforcement"
    },
    {
      "id": "hr9349-118",
      "type": "hr",
      "number": "9349",
      "congress": 118,
      "title": "American CANS Act",
      "introduced_date": "2024-08-13",
      "latest_action": {
        "date": "2024-12-17",
        "text": "Referred to the Subcommittee on Trade."
      },
      "policy_area": "Foreign Trade and International Finance"
    },
    {
      "id": "hr9258-118",
      "type": "hr",
      "number": "9258",
      "congress": 118,
      "title": "Disrupt Fentanyl Pill Production Act",
      "introduced_date": "2024-08-02",
      "latest_action": {
        "date": "2024-08-02",
        "text": "Referred to the Committee on Energy and Commerce, and in addition to the Committee on the Judiciary, for a period to be subsequently determined by the Speaker, in each case for consideration of such provisions as fall within the jurisdiction of the committee concerned."
      },
      "policy_area": "Health"
    },
    {
      "id": "hr9150-118",
      "type": "hr",
      "number": "9150",
      "congress": 118,
      "title": "Keeping Families Safe from Wildfire Smoke Act",
      "introduced_date": "2024-07-25",
      "latest_action": {
        "date": "2024-07-26",
        "text": "Referred to the Subcommittee on Economic Development, Public Buildings, and Emergency Management."
      },
      "policy_area": "Emergency Management"
    },
    {
      "id": "hr9068-118",
      "type": "hr",
      "number": "9068",
      "congress": 118,
      "title": "Child Care Workforce and Facilities Act of 2024",
      "introduced_date": "2024-07-18",
      "latest_action": {
        "date": "2024-07-18",
        "text": "Referred to the House Committee on Education and the Workforce."
      },
      "policy_area": "Families"
    },
    {
      "id": "hr9009-118",
      "type": "hr",
      "number": "9009",
      "congress": 118,
      "title": "Gas Prices Relief Act of 2024",
      "introduced_date": "2024-07-11",
      "latest_action": {
        "date": "2024-07-11",
        "text": "Referred to the House Committee on Ways and Means."
      },
      "policy_area": "Taxation"
    },
    {
      "id": "hr8656-118",
      "type": "hr",
      "number": "8656",
      "congress": 118,
      "title": "Modernizing Wildfire Safety and Prevention Act of 2024",
      "introduced_date": "2024-06-07",
      "latest_action": {
        "date": "2024-09-03",
        "text": "Referred to the Subcommittee on Forestry."
      },
      "policy_area": "Emergency Management"
    },
    {
      "id": "hr8308-118",
      "type": "hr",
      "number": "8308",
      "congress": 118,
      "title": "Nutria Eradication and Control Reauthorization Act of 2024",
      "introduced_date": "2024-05-08",
      "latest_action": {
        "date": "2024-12-18",
        "text": "Received in the Senate and Read twice and referred to the Committee on Environment and Public Works."
      },
      "policy_area": "Environmental Protection"
    },
    {
      "id": "hr8002-118",
      "type": "hr",
      "number": "8002",
      "congress": 118,
      "title": "Stop the Rate Hikes Act",
      "introduced_date": "2024-04-15",
      "latest_action": {
        "date": "2024-04-19",
        "text": "Referred to the Subcommittee on Energy, Climate and Grid Security."
      },
      "policy_area": "Energy"
    },
    {
      "id": "hr6968-118",
      "type": "hr",
      "number": "6968",
      "congress": 118,
      "title": "Bringing More Therapists to the Valley Act of 2024",
      "introduced_date": "2024-01-11",
      "latest_action": {
        "date": "2024-01-12",
        "text": "Referred to the Subcommittee on Health."
      },
      "policy_area": "Health"
    },
    {
      "id": "hr6340-118",
      "type": "hr",
      "number": "6340",
      "congress": 118,
      "title": "Improving Housing Outcomes for Veterans Act of 2023",
      "introduced_date": "2023-11-09",
      "latest_action": {
        "date": "2023-11-27",
        "text": "Referred to the Subcommittee on Economic Opportunity."
      },
      "policy_area": "Armed Forces and National Security"
    },
    {
      "id": "hr5992-118",
      "type": "hr",
      "number": "5992",
      "congress": 118,
      "title": "Protecting Farmers from Drought Act of 2023",
      "introduced_date": "2023-10-19",
      "latest_action": {
        "date": "2024-01-18",
        "text": "Referred to the Subcommittee on General Farm Commodities, Risk Management, and Credit."
      },
      "policy_area": "Agriculture and Food"
    },
    {
      "id": "hr5941-118",
      "type": "hr",
      "number": "5941",
      "congress": 118,
      "title": "Ban Corporate PACs Act",
      "introduced_date": "2023-10-12",
      "latest_action": {
        "date": "2023-10-25",
        "text": "Referred to the House Committee on House Administration."
      },
      "policy_area": "Government Operations and Politics"
    },
    {
      "id": "hr5756-118",
      "type": "hr",
      "number": "5756",
      "congress": 118,
      "title": "Protect Families from Toxic Algal Blooms Act",
      "introduced_date": "2023-09-27",
      "latest_action": {
        "date": "2023-09-27",
        "text": "Referred to the House Committee on Science, Space, and Technology."
      },
      "policy_area": "Environmental Protection"
    },
    {
      "id": "hr5637-118",
      "type": "hr",
      "number": "5637",
      "congress": 118,
      "title": "Supporting Farmworker Mental Health Act",
      "introduced_date": "2023-09-21",
      "latest_action": {
        "date": "2023-09-21",
        "text": "Referred to the House Committee on Agriculture."
      },
      "policy_area": "Agriculture and Food"
    },
    {
      "id": "hr5483-118",
      "type": "hr",
      "number": "5483",
      "congress": 118,
      "title": "Securing Access for the central Valley and Enhancing (SAVE) Water Resources Act",
      "introduced_date": "2023-09-14",
      "latest_action": {
        "date": "2023-09-14",
        "text": "Referred to the House Committee on Natural Resources."
      },
      "policy_area": "Water Resources Development"
    },
    {
      "id": "hr5329-118",
      "type": "hr",
      "number": "5329",
      "congress": 118,
      "title": "Wildfire Smoke Emergency Declaration Act of 2023",
      "introduced_date": "2023-09-01",
      "latest_action": {
        "date": "2023-09-05",
        "text": "Referred to the Subcommittee on Economic Development, Public Buildings, and Emergency Management."
      },
      "policy_area": "Emergency Management"
    },
    {
      "id": "hr5304-118",
      "type": "hr",
      "number": "5304",
      "congress": 118,
      "title": "Safeguarding Our Levees Act",
      "introduced_date": "2023-08-29",
      "latest_action": {
        "date": "2023-08-30",
        "text": "Referred to the Subcommittee on Water Resources and Environment."
      },
      "policy_area": "Water Resources Development"
    },
    {
      "id": "hr4911-118",
      "type": "hr",
      "number": "4911",
      "congress": 118,
      "title": "Supporting the Health and Safety of Law Enforcement Act of 2023",
      "introduced_date": "2023-07-26",
      "latest_action": {
        "date": "2023-07-26",
        "text": "Referred to the House Committee on the Judiciary."
      },
      "policy_area": "Crime and Law Enforcement"
    },
    {
      "id": "hr4680-118",
      "type": "hr",
      "number": "4680",
      "congress": 118,
      "title": "Train More Doctors Act of 2023",
      "introduced_date": "2023-07-17",
      "latest_action": {
        "date": "2024-12-17",
        "text": "Referred to the Subcommittee on Health."
      },
      "policy_area": "Health"
    },
    {
      "id": "hr4617-118",
      "type": "hr",
      "number": "4617",
      "congress": 118,
      "title": "Pyrolysis Innovation Grants Act",
      "introduced_date": "2023-07-13",
      "latest_action": {
        "date": "2023-08-24",
        "text": "Referred to the Subcommittee on Conservation, Research, and Biotechnology."
      },
      "policy_area": "Agriculture and Food"
    },
    {
      "id": "hr4246-118",
      "type": "hr",
      "number": "4246",
      "congress": 118,
      "title": "Investing in Community Safety Act of 2023",
      "introduced_date": "2023-06-21",
      "latest_action": {
        "date": "2023-06-21",
        "text": "Referred to the House Committee on the Judiciary."
      },
      "policy_area": "Crime and Law Enforcement"
    },
    {
      "id": "hr4247-118",
      "type": "hr",
      "number": "4247",
      "congress": 118,
      "title": "Flood Prevention and Snowpack Management Act",
      "introduced_date": "2023-06-21",
      "latest_action": {
        "date": "2023-06-22",
        "text": "Referred to the Subcommittee on Water Resources and Environment."
      },
      "policy_area": "Water Resources Development"
    },
    {
      "id": "hr4066-118",
      "type": "hr",
      "number": "4066",
      "congress": 118,
      "title": "Investing in Our Crops Act",
      "introduced_date": "2023-06-13",
      "latest_action": {
        "date": "2023-09-26",
        "text": "Referred to the Subcommittee on Conservation, Research, and Biotechnology."
      },
      "policy_area": "Agriculture and Food"
    },
    {
      "id": "hr3814-118",
      "type": "hr",
      "number": "3814",
      "congress": 118,
      "title": "Future of Agricultural Resiliency And Modernization Act",
      "introduced_date": "2023-06-05",
      "latest_action": {
        "date": "2023-07-10",
        "text": "Referred to the Subcommittee on Conservation, Research, and Biotechnology."
      },
      "policy_area": "Agriculture and Food"
    },
    {
      "id": "hr3786-118",
      "type": "hr",
      "number": "3786",
      "congress": 118,
      "title": "Apprenticeships to College Act",
      "introduced_date": "2023-06-01",
      "latest_action": {
        "date": "2023-06-01",
        "text": "Referred to the House Committee on Education and the Workforce."
      },
      "policy_area": "Labor and Employment"
    },
    {
      "id": "hr3416-118",
      "type": "hr",
      "number": "3416",
      "congress": 118,
      "title": "Youth Workforce Readiness Act of 2023",
      "introduced_date": "2023-05-17",
      "latest_action": {
        "date": "2023-05-17",
        "text": "Referred to the House Committee on Education and the Workforce."
      },
      "policy_area": "Labor and Employment"
    },
    {
      "id": "hr3396-118",
      "type": "hr",
      "number": "3396",
      "congress": 118,
      "title": "Fire Department Repayment Act of 2023",
      "introduced_date": "2023-05-17",
      "latest_action": {
        "date": "2024-12-18",
        "text": "Received in the Senate and Read twice and referred to the Committee on Homeland Security and Governmental Affairs."
      },
      "policy_area": "Public Lands and Natural Resources"
    },
    {
      "id": "hr3369-118",
      "type": "hr",
      "number": "3369",
      "congress": 118,
      "title": "Artificial Intelligence Accountability Act",
      "introduced_date": "2023-05-16",
      "latest_action": {
        "date": "2023-10-25",
        "text": "Placed on the Union Calendar, Calendar No. 195."
      },
      "policy_area": "Science, Technology, Communications"
    },
    {
      "id": "hr3055-118",
      "type": "hr",
      "number": "3055",
      "congress": 118,
      "title": "Improving Mental Health in Schools Act",
      "introduced_date": "2023-05-02",
      "latest_action": {
        "date": "2023-05-02",
        "text": "Referred to the House Committee on Education and the Workforce."
      },
      "policy_area": "Education"
    },
    {
      "id": "hr2596-118",
      "type": "hr",
      "number": "2596",
      "congress": 118,
      "title": "Stop PG&E Price Gouging During Emergencies Act",
      "introduced_date": "2023-04-13",
      "latest_action": {
        "date": "2023-04-21",
        "text": "Referred to the Subcommittee on Energy, Climate and Grid Security."
      },
      "policy_area": "Commerce"
    },
    {
      "id": "hr924-118",
      "type": "hr",
      "number": "924",
      "congress": 118,
      "title": "Stop the Delta Tunnel Act",
      "introduced_date": "2023-02-09",
      "latest_action": {
        "date": "2023-02-10",
        "text": "Referred to the Subcommittee on Water Resources and Environment."
      },
      "policy_area": "Water Resources Development"
    },
    {
      "id": "hr9386-117",
      "type": "hr",
      "number": "9386",
      "congress": 117,
      "title": "Better Data for Cleaner Air Act of 2022",
      "introduced_date": "2022-12-01",
      "latest_action": {
        "date": "2022-12-01",
        "text": "Referred to the House Committee on Energy and Commerce."
      },
      "policy_area": "Environmental Protection"
    },
    {
      "id": "hr9370-117",
      "type": "hr",
      "number": "9370",
      "congress": 117,
      "title": "Bring our Small Businesses Back Act",
      "introduced_date": "2022-11-30",
      "latest_action": {
        "date": "2022-11-30",
        "text": "Referred to the House Committee on Small Business."
      },
      "policy_area": "Commerce"
    },
    {
      "id": "hr9156-117",
      "type": "hr",
      "number": "9156",
      "congress": 117,
      "title": "Train More Doctors Act of 2022",
      "introduced_date": "2022-10-07",
      "latest_action": {
        "date": "2022-10-10",
        "text": "Referred to the Subcommittee on Health."
      },
      "policy_area": "Health"
    },
    {
      "id": "hr9155-117",
      "type": "hr",
      "number": "9155",
      "congress": 117,
      "title": "No Bonuses for Executives Act of 2022",
      "introduced_date": "2022-10-07",
      "latest_action": {
        "date": "2022-10-07",
        "text": "Referred to the House Committee on Ways and Means."
      },
      "policy_area": "Taxation"
    },
    {
      "id": "hr8849-117",
      "type": "hr",
      "number": "8849",
      "congress": 117,
      "title": "Stop Delta Tunnels Act",
      "introduced_date": "2022-09-15",
      "latest_action": {
        "date": "2022-09-16",
        "text": "Referred to the Subcommittee on Water Resources and Environment."
      },
      "policy_area": "Water Resources Development"
    },
    {
      "id": "hr8613-117",
      "type": "hr",
      "number": "8613",
      "congress": 117,
      "title": "Supporting the Health and Safety of Law Enforcement Act of 2022",
      "introduced_date": "2022-07-29",
      "latest_action": {
        "date": "2022-11-01",
        "text": "Referred to the Subcommittee on Crime, Terrorism, and Homeland Security."
      },
      "policy_area": "Crime and Law Enforcement"
    },
    {
      "id": "hr8035-117",
      "type": "hr",
      "number": "8035",
      "congress": 117,
      "title": "Fire Department Repayment Act of 2022",
      "introduced_date": "2022-06-13",
      "latest_action": {
        "date": "2022-06-30",
        "text": "Referred to the Subcommittee on Conservation and Forestry."
      },
      "policy_area": "Public Lands and Natural Resources"
    },
    {
      "id": "hr7764-117",
      "type": "hr",
      "number": "7764",
      "congress": 117,
      "title": "To direct the Secretary of Agriculture to provide additional payments under the environmental quality incentives program for implementation of a nutrient management practice, and for other purposes.",
      "introduced_date": "2022-05-13",
      "latest_action": {
        "date": "2022-06-03",
        "text": "Placed on the Union Calendar, Calendar No. 257."
      },
      "policy_area": "Agriculture and Food"
    },
    {
      "id": "hr7463-117",
      "type": "hr",
      "number": "7463",
      "congress": 117,
      "title": "Gas Price Gouging Prevention Act",
      "introduced_date": "2022-04-07",
      "latest_action": {
        "date": "2022-04-08",
        "text": "Referred to the Subcommittee on Consumer Protection and Commerce."
      },
      "policy_area": "Commerce"
    },
    {
      "id": "hr7271-117",
      "type": "hr",
      "number": "7271",
      "congress": 117,
      "title": "Putting Gas Money Back In Your Pocket Act",
      "introduced_date": "2022-03-29",
      "latest_action": {
        "date": "2022-03-29",
        "text": "Referred to the House Committee on Ways and Means."
      },
      "policy_area": "Taxation"
    },
    {
      "id": "hr6709-117",
      "type": "hr",
      "number": "6709",
      "congress": 117,
      "title": "Improving Mental Health in Schools Act",
      "introduced_date": "2022-02-11",
      "latest_action": {
        "date": "2022-02-11",
        "text": "Referred to the House Committee on Education and Labor."
      },
      "policy_area": "Education"
    },
    {
      "id": "hr6384-117",
      "type": "hr",
      "number": "6384",
      "congress": 117,
      "title": "Improving Awareness of Health Coverage Options Act of 2022",
      "introduced_date": "2022-01-12",
      "latest_action": {
        "date": "2022-01-13",
        "text": "Referred to the Subcommittee on Health."
      },
      "policy_area": "Health"
    },
    {
      "id": "hr6224-117",
      "type": "hr",
      "number": "6224",
      "congress": 117,
      "title": "Fix the Unemployment Backlogs Act",
      "introduced_date": "2021-12-09",
      "latest_action": {
        "date": "2021-12-09",
        "text": "Referred to the House Committee on Ways and Means."
      },
      "policy_area": "Labor and Employment"
    },
    {
      "id": "hres792-117",
      "type": "hres",
      "number": "792",
      "congress": 117,
      "title": "Honoring the individuals fighting and the individuals who have fallen responding to wildland fires during the ongoing 2021 wildfire season.",
      "introduced_date": "2021-11-12",
      "latest_action": {
        "date": "2021-11-15",
        "text": "Referred to the Subcommittee on National Parks, Forests, and Public Lands."
      },
      "policy_area": "Emergency Management"
    },
    {
      "id": "hr5716-117",
      "type": "hr",
      "number": "5716",
      "congress": 117,
      "title": "Securing Access for the central Valley and Enhancing (SAVE) Water Resources Act",
      "introduced_date": "2021-10-25",
      "latest_action": {
        "date": "2021-10-29",
        "text": "Referred to the Subcommittee on Water, Oceans, and Wildlife."
      },
      "policy_area": "Water Resources Development"
    },
    {
      "id": "hr4763-117",
      "type": "hr",
      "number": "4763",
      "congress": 117,
      "title": "Future of Agricultural Resiliency And Modernization Act",
      "introduced_date": "2021-07-28",
      "latest_action": {
        "date": "2021-08-18",
        "text": "Referred to the Subcommittee on Conservation and Forestry."
      },
      "policy_area": "Agriculture and Food"
    },
    {
      "id": "hr5589-117",
      "type": "hr",
      "number": "5589",
      "congress": 117,
      "title": "Pyrolysis Innovation Grants Act",
      "introduced_date": "2021-10-15",
      "latest_action": {
        "date": "2021-11-01",
        "text": "Placed on the Union Calendar, Calendar No. 122."
      },
      "policy_area": "Agriculture and Food"
    },
    {
      "id": "hr5562-117",
      "type": "hr",
      "number": "5562",
      "congress": 117,
      "title": "To amend title 38, United States Code, to expand eligibility for hospital care, medical services, and nursing home care from the Department of Veterans Affairs to include veterans of World War II.",
      "introduced_date": "2021-10-12",
      "latest_action": {
        "date": "2021-11-04",
        "text": "Ordered to be Reported by Voice Vote."
      },
      "policy_area": "Armed Forces and National Security"
    },
    {
      "id": "hr5252-117",
      "type": "hr",
      "number": "5252",
      "congress": 117,
      "title": "Connecting Students to Great Jobs Act",
      "introduced_date": "2021-09-14",
      "latest_action": {
        "date": "2021-09-14",
        "text": "Referred to the House Committee on Education and Labor."
      },
      "policy_area": "Labor and Employment"
    },
    {
      "id": "hres550-117",
      "type": "hres",
      "number": "550",
      "congress": 117,
      "title": "Expressing the sense of the House of Representatives regarding United States policy recognizing the Assyrian Genocide.",
      "introduced_date": "2021-07-22",
      "latest_action": {
        "date": "2021-08-04",
        "text": "Referred to the Subcommittee on Middle East, North Africa and Global Counterterrorism."
      },
      "policy_area": "International Affairs"
    },
    {
      "id": "hr4090-117",
      "type": "hr",
      "number": "4090",
      "congress": 117,
      "title": "Making Education Affordable and Accessible Act",
      "introduced_date": "2021-06-23",
      "latest_action": {
        "date": "2021-06-23",
        "text": "Referred to the House Committee on Education and Labor."
      },
      "policy_area": "Education"
    },
    {
      "id": "hr3765-117",
      "type": "hr",
      "number": "3765",
      "congress": 117,
      "title": "Disability Employment Incentive Act",
      "introduced_date": "2021-06-08",
      "latest_action": {
        "date": "2021-06-08",
        "text": "Referred to the House Committee on Ways and Means."
      },
      "policy_area": "Taxation"
    },
    {
      "id": "hr3663-117",
      "type": "hr",
      "number": "3663",
      "congress": 117,
      "title": "Apprenticeships to College Act",
      "introduced_date": "2021-06-01",
      "latest_action": {
        "date": "2021-06-01",
        "text": "Referred to the House Committee on Education and Labor."
      },
      "policy_area": "Labor and Employment"
    },
    {
      "id": "hr3342-117",
      "type": "hr",
      "number": "3342",
      "congress": 117,
      "title": "Youth Workforce Readiness Act of 2021",
      "introduced_date": "2021-05-19",
      "latest_action": {
        "date": "2021-05-19",
        "text": "Referred to the House Committee on Education and Labor."
      },
      "policy_area": "Labor and Employment"
    },
    {
      "id": "hr2781-117",
      "type": "hr",
      "number": "2781",
      "congress": 117,
      "title": "Water Resources Research Amendments Act",
      "introduced_date": "2021-04-22",
      "latest_action": {
        "date": "2021-06-15",
        "text": "Referred to the Subcommittee on Water, Oceans, and Wildlife."
      },
      "policy_area": "Water Resources Development"
    },
    {
      "id": "hr2692-117",
      "type": "hr",
      "number": "2692",
      "congress": 117,
      "title": "Ban Corporate PACs Act",
      "introduced_date": "2021-04-20",
      "latest_action": {
        "date": "2021-04-20",
        "text": "Referred to the House Committee on House Administration."
      },
      "policy_area": "Government Operations and Politics"
    },
    {
      "id": "hres288-117",
      "type": "hres",
      "number": "288",
      "congress": 117,
      "title": "Recognizing the cultural and historical significance of the Assyrian New Year.",
      "introduced_date": "2021-04-01",
      "latest_action": {
        "date": "2021-04-01",
        "text": "Referred to the House Committee on Foreign Affairs."
      },
      "policy_area": "International Affairs"
    },
    {
      "id": "hr1972-117",
      "type": "hr",
      "number": "1972",
      "congress": 117,
      "title": "Fair Care for Vietnam Veterans Act of 2021",
      "introduced_date": "2021-03-17",
      "latest_action": {
        "date": "2021-06-16",
        "text": "Referred to the Subcommittee on Disability Assistance and Memorial Affairs."
      },
      "policy_area": "Armed Forces and National Security"
    },
    {
      "id": "hr1133-117",
      "type": "hr",
      "number": "1133",
      "congress": 117,
      "title": "To amend the Higher Education Act of 1965 to include certain employment as a health care practitioner as eligible for public service loan forgiveness, and for other purposes.",
      "introduced_date": "2021-02-18",
      "latest_action": {
        "date": "2021-02-18",
        "text": "Referred to the House Committee on Education and Labor."
      },
      "policy_area": "Education"
    },
    {
      "id": "hr995-117",
      "type": "hr",
      "number": "995",
      "congress": 117,
      "title": "To amend the Child Abuse Prevention and Treatment Act to authorize the Secretary of Health and Human Services to award grants for purposes of reducing child abuse and neglect due to the substance use disorder of a parent or caregiver.",
      "introduced_date": "2021-02-11",
      "latest_action": {
        "date": "2021-02-11",
        "text": "Referred to the House Committee on Education and Labor."
      },
      "policy_area": "Families"
    },
    {
      "id": "hr540-117",
      "type": "hr",
      "number": "540",
      "congress": 117,
      "title": "Child Care Workforce and Facilities Act of 2021",
      "introduced_date": "2021-01-28",
      "latest_action": {
        "date": "2021-01-28",
        "text": "Referred to the House Committee on Education and Labor."
      },
      "policy_area": "Families"
    },
    {
      "id": "hr8421-116",
      "type": "hr",
      "number": "8421",
      "congress": 116,
      "title": "Wildfire Smoke Relief Act",
      "introduced_date": "2020-09-29",
      "latest_action": {
        "date": "2020-09-30",
        "text": "Referred to the Subcommittee on Economic Development, Public Buildings, and Emergency Management."
      },
      "policy_area": "Emergency Management"
    },
    {
      "id": "hr8328-116",
      "type": "hr",
      "number": "8328",
      "congress": 116,
      "title": "Apprenticeships to College Act",
      "introduced_date": "2020-09-21",
      "latest_action": {
        "date": "2020-09-21",
        "text": "Referred to the House Committee on Education and Labor."
      },
      "policy_area": "Labor and Employment"
    },
    {
      "id": "hr8315-116",
      "type": "hr",
      "number": "8315",
      "congress": 116,
      "title": "Safe Indoor Spaces Act",
      "introduced_date": "2020-09-18",
      "latest_action": {
        "date": "2020-09-18",
        "text": "Referred to the House Committee on Energy and Commerce."
      },
      "policy_area": "Health"
    },
    {
      "id": "hr8041-116",
      "type": "hr",
      "number": "8041",
      "congress": 116,
      "title": "Snow Water Supply Forecasting Program Authorization Act",
      "introduced_date": "2020-08-14",
      "latest_action": {
        "date": "2020-09-04",
        "text": "Referred to the Subcommittee on Water, Oceans, and Wildlife."
      },
      "policy_area": "Water Resources Development"
    },
    {
      "id": "hr7874-116",
      "type": "hr",
      "number": "7874",
      "congress": 116,
      "title": "Construction Jobs During Coronavirus Act",
      "introduced_date": "2020-07-30",
      "latest_action": {
        "date": "2020-07-30",
        "text": "Referred to the Subcommittee on Select Revenue Measures."
      },
      "policy_area": "Taxation"
    },
    {
      "id": "hr7745-116",
      "type": "hr",
      "number": "7745",
      "congress": 116,
      "title": "Protecting Fairs During Coronavirus Act",
      "introduced_date": "2020-07-23",
      "latest_action": {
        "date": "2020-07-23",
        "text": "Referred to the House Committee on Agriculture."
      },
      "policy_area": "Agriculture and Food"
    },
    {
      "id": "hr7685-116",
      "type": "hr",
      "number": "7685",
      "congress": 116,
      "title": "Protecting Seniors from Scams Act",
      "introduced_date": "2020-07-20",
      "latest_action": {
        "date": "2020-07-20",
        "text": "Referred to the Subcommittee on Trade."
      },
      "policy_area": "Commerce"
    },
    {
      "id": "hr7530-116",
      "type": "hr",
      "number": "7530",
      "congress": 116,
      "title": "Protecting Students from Cybercrimes Act",
      "introduced_date": "2020-07-09",
      "latest_action": {
        "date": "2020-07-09",
        "text": "Referred to the Committee on Education and Labor, and in addition to the Committee on the Judiciary, for a period to be subsequently determined by the Speaker, in each case for consideration of such provisions as fall within the jurisdiction of the committee concerned."
      },
      "policy_area": "Education"
    },
    {
      "id": "hr7482-116",
      "type": "hr",
      "number": "7482",
      "congress": 116,
      "title": "Future of Agricultural Resiliency And Modernization Act",
      "introduced_date": "2020-07-02",
      "latest_action": {
        "date": "2020-08-13",
        "text": "Referred to the Subcommittee on Conservation and Forestry."
      },
      "policy_area": "Agriculture and Food"
    },
    {
      "id": "hr7459-116",
      "type": "hr",
      "number": "7459",
      "congress": 116,
      "title": "Coronavirus Service Corps Act",
      "introduced_date": "2020-07-01",
      "latest_action": {
        "date": "2020-07-01",
        "text": "Referred to the House Committee on Education and Labor."
      },
      "policy_area": "Labor and Employment"
    },
    {
      "id": "hr7210-116",
      "type": "hr",
      "number": "7210",
      "congress": 116,
      "title": "Budget Transparency Act",
      "introduced_date": "2020-06-15",
      "latest_action": {
        "date": "2020-06-15",
        "text": "Referred to the House Committee on the Budget."
      },
      "policy_area": "Economics and Public Finance"
    },
    {
      "id": "hr6717-116",
      "type": "hr",
      "number": "6717",
      "congress": 116,
      "title": "Health Care Workforce Protection Act of 2020",
      "introduced_date": "2020-05-05",
      "latest_action": {
        "date": "2020-05-05",
        "text": "Referred to the House Committee on the Judiciary."
      },
      "policy_area": "Immigration"
    },
    {
      "id": "hr6564-116",
      "type": "hr",
      "number": "6564",
      "congress": 116,
      "title": "Fresh Produce for Kids in Need Act",
      "introduced_date": "2020-04-21",
      "latest_action": {
        "date": "2020-04-21",
        "text": "Referred to the House Committee on Education and Labor."
      },
      "policy_area": "Agriculture and Food"
    },
    {
      "id": "hr6502-116",
      "type": "hr",
      "number": "6502",
      "congress": 116,
      "title": "COVID-19 Graduate Relief Act",
      "introduced_date": "2020-04-14",
      "latest_action": {
        "date": "2020-04-14",
        "text": "Referred to the House Committee on Education and Labor."
      },
      "policy_area": "Education"
    },
    {
      "id": "hr6351-116",
      "type": "hr",
      "number": "6351",
      "congress": 116,
      "title": "Universal Coronavirus Vaccine Act",
      "introduced_date": "2020-03-23",
      "latest_action": {
        "date": "2020-03-23",
        "text": "Referred to the House Committee on Energy and Commerce."
      },
      "policy_area": "Health"
    },
    {
      "id": "hr6221-116",
      "type": "hr",
      "number": "6221",
      "congress": 116,
      "title": "Paid Sick Leave Credit Act of 2020",
      "introduced_date": "2020-03-12",
      "latest_action": {
        "date": "2020-03-12",
        "text": "Referred to the House Committee on Ways and Means."
      },
      "policy_area": "Taxation"
    },
    {
      "id": "hr6130-116",
      "type": "hr",
      "number": "6130",
      "congress": 116,
      "title": "Improving Awareness of Health Coverage Options Act",
      "introduced_date": "2020-03-09",
      "latest_action": {
        "date": "2020-03-09",
        "text": "Referred to the House Committee on Education and Labor."
      },
      "policy_area": "Health"
    },
    {
      "id": "hr5755-116",
      "type": "hr",
      "number": "5755",
      "congress": 116,
      "title": "No Pensions for Corrupt Politicians Act of 2020",
      "introduced_date": "2020-02-04",
      "latest_action": {
        "date": "2020-02-04",
        "text": "Referred to the Committee on House Administration, and in addition to the Committee on Oversight and Reform, for a period to be subsequently determined by the Speaker, in each case for consideration of such provisions as fall within the jurisdiction of the committee concerned."
      },
      "policy_area": "Government Operations and Politics"
    },
    {
      "id": "hr5610-116",
      "type": "hr",
      "number": "5610",
      "congress": 116,
      "title": "Fair Care for Vietnam Veterans Act",
      "introduced_date": "2020-01-15",
      "latest_action": {
        "date": "2020-01-15",
        "text": "Referred to the House Committee on Veterans' Affairs."
      },
      "policy_area": "Armed Forces and National Security"
    },
    {
      "id": "hr5609-116",
      "type": "hr",
      "number": "5609",
      "congress": 116,
      "title": "Homelessness Emergency Declaration Act",
      "introduced_date": "2020-01-15",
      "latest_action": {
        "date": "2020-01-16",
        "text": "Referred to the Subcommittee on Economic Development, Public Buildings, and Emergency Management."
      },
      "policy_area": "Housing and Community Development"
    },
    {
      "id": "hr5411-116",
      "type": "hr",
      "number": "5411",
      "congress": 116,
      "title": "Increasing Access to Mental Health Act of 2019",
      "introduced_date": "2019-12-12",
      "latest_action": {
        "date": "2019-12-13",
        "text": "Referred to the Subcommittee on Health."
      },
      "policy_area": "Health"
    },
    {
      "id": "hr5258-116",
      "type": "hr",
      "number": "5258",
      "congress": 116,
      "title": "No Bonuses During Blackouts Act of 2019",
      "introduced_date": "2019-11-22",
      "latest_action": {
        "date": "2019-11-22",
        "text": "Referred to the House Committee on Ways and Means."
      },
      "policy_area": "Taxation"
    },
    {
      "id": "-116",
      "type": "",
      "number": "",
      "congress": 116,
      "title": "",
      "introduced_date": "2019-11-21",
      "latest_action": {
        "date": "2019-11-21",
        "text": "On agreeing to the Harder (CA) amendment (A004) Agreed to by recorded vote: 414 - 1 (Roll no. 638). "
      },
      "policy_area": null
    },
    {
      "id": "hr5236-116",
      "type": "hr",
      "number": "5236",
      "congress": 116,
      "title": "Youth Workforce Readiness Act of 2019",
      "introduced_date": "2019-11-21",
      "latest_action": {
        "date": "2019-11-21",
        "text": "Referred to the House Committee on Education and Labor."
      },
      "policy_area": "Labor and Employment"
    },
    {
      "id": "hres729-116",
      "type": "hres",
      "number": "729",
      "congress": 116,
      "title": "Encouraging the President to expand the list of the Department of Veterans Affairs of presumptive medical conditions associated with exposure to Agent Orange to include Parkinsonism, bladder cancer, hypertension, and hypothyroidism.",
      "introduced_date": "2019-11-21",
      "latest_action": {
        "date": "2019-11-21",
        "text": "Referred to the Committee on Veterans' Affairs, and in addition to the Committee on Armed Services, for a period to be subsequently determined by the Speaker, in each case for consideration of such provisions as fall within the jurisdiction of the committee concerned."
      },
      "policy_area": "Armed Forces and National Security"
    },
    {
      "id": "hr5190-116",
      "type": "hr",
      "number": "5190",
      "congress": 116,
      "title": "STAR Act",
      "introduced_date": "2019-11-20",
      "latest_action": {
        "date": "2019-11-21",
        "text": "Referred to the Subcommittee on Health."
      },
      "policy_area": "Health"
    },
    {
      "id": "hr4607-116",
      "type": "hr",
      "number": "4607",
      "congress": 116,
      "title": "To amend the Higher Education Act of 1965 to include certain employment as a health care practitioner as eligible for public service loan forgiveness, and for other purposes.",
      "introduced_date": "2019-10-04",
      "latest_action": {
        "date": "2019-10-04",
        "text": "Referred to the House Committee on Education and Labor."
      },
      "policy_area": "Education"
    },
    {
      "id": "hr4356-116",
      "type": "hr",
      "number": "4356",
      "congress": 116,
      "title": "Protecting Families of Fallen Servicemembers Act",
      "introduced_date": "2019-09-17",
      "latest_action": {
        "date": "2021-01-05",
        "text": "Became Public Law No: 116-285."
      },
      "policy_area": "Armed Forces and National Security"
    },
    {
      "id": "hr4247-116",
      "type": "hr",
      "number": "4247",
      "congress": 116,
      "title": "Financial Watchdog Support Act",
      "introduced_date": "2019-09-09",
      "latest_action": {
        "date": "2019-09-18",
        "text": "Referred to the Subcommittee on Commodity Exchanges, Energy, and Credit."
      },
      "policy_area": "Finance and Financial Sector"
    },
    {
      "id": "hr4210-116",
      "type": "hr",
      "number": "4210",
      "congress": 116,
      "title": "Fair Pay for the Modesto VA Act",
      "introduced_date": "2019-08-27",
      "latest_action": {
        "date": "2019-08-27",
        "text": "Referred to the House Committee on Oversight and Reform."
      },
      "policy_area": "Armed Forces and National Security"
    },
    {
      "id": "hres537-116",
      "type": "hres",
      "number": "537",
      "congress": 116,
      "title": "Expressing the sense of the House of Representatives regarding United States policy recognizing the Assyrian Genocide.",
      "introduced_date": "2019-08-02",
      "latest_action": {
        "date": "2019-08-02",
        "text": "Referred to the House Committee on Foreign Affairs."
      },
      "policy_area": "International Affairs"
    },
    {
      "id": "hr3992-116",
      "type": "hr",
      "number": "3992",
      "congress": 116,
      "title": "Disability Employment Incentive Act",
      "introduced_date": "2019-07-25",
      "latest_action": {
        "date": "2019-07-25",
        "text": "Referred to the House Committee on Ways and Means."
      },
      "policy_area": "Taxation"
    },
    {
      "id": "hr3892-116",
      "type": "hr",
      "number": "3892",
      "congress": 116,
      "title": "START Career Pathways Act",
      "introduced_date": "2019-07-23",
      "latest_action": {
        "date": "2019-07-23",
        "text": "Referred to the House Committee on Education and Labor."
      },
      "policy_area": "Labor and Employment"
    },
    {
      "id": "hr3893-116",
      "type": "hr",
      "number": "3893",
      "congress": 116,
      "title": "School to Career Pathways Act of 2019",
      "introduced_date": "2019-07-23",
      "latest_action": {
        "date": "2019-07-23",
        "text": "Referred to the House Committee on Education and Labor."
      },
      "policy_area": "Education"
    },
    {
      "id": "hr3891-116",
      "type": "hr",
      "number": "3891",
      "congress": 116,
      "title": "Making Education Affordable and Accessible Act",
      "introduced_date": "2019-07-23",
      "latest_action": {
        "date": "2019-07-23",
        "text": "Referred to the House Committee on Education and Labor."
      },
      "policy_area": "Education"
    },
    {
      "id": "hr3752-116",
      "type": "hr",
      "number": "3752",
      "congress": 116,
      "title": "Stop Discrimination Against Veteran Home Buyers Act",
      "introduced_date": "2019-07-15",
      "latest_action": {
        "date": "2019-08-14",
        "text": "Referred to the Subcommittee on Economic Opportunity."
      },
      "policy_area": "Armed Forces and National Security"
    },
    {
      "id": "hr3510-116",
      "type": "hr",
      "number": "3510",
      "congress": 116,
      "title": "Water Resources Research Amendments Act",
      "introduced_date": "2019-06-26",
      "latest_action": {
        "date": "2019-07-25",
        "text": "Subcommittee Hearings Held."
      },
      "policy_area": "Water Resources Development"
    },
    {
      "id": "hr3400-116",
      "type": "hr",
      "number": "3400",
      "congress": 116,
      "title": "ENLIST Act",
      "introduced_date": "2019-06-21",
      "latest_action": {
        "date": "2019-06-24",
        "text": "Referred to the Subcommittee on Military Personnel."
      },
      "policy_area": "Armed Forces and National Security"
    },
    {
      "id": "hr3399-116",
      "type": "hr",
      "number": "3399",
      "congress": 116,
      "title": "To amend the Nutria Eradication and Control Act of 2003 to include California in the program, and for other purposes.",
      "introduced_date": "2019-06-21",
      "latest_action": {
        "date": "2020-10-30",
        "text": "Became Public Law No: 116-186."
      },
      "policy_area": "Environmental Protection"
    },
    {
      "id": "hr3271-116",
      "type": "hr",
      "number": "3271",
      "congress": 116,
      "title": "No Health Care, No Raise Act",
      "introduced_date": "2019-06-13",
      "latest_action": {
        "date": "2019-06-13",
        "text": "Referred to the Committee on House Administration, and in addition to the Committee on Oversight and Reform, for a period to be subsequently determined by the Speaker, in each case for consideration of such provisions as fall within the jurisdiction of the committee concerned."
      },
      "policy_area": "Congress"
    },
    {
      "id": "-116",
      "type": "",
      "number": "",
      "congress": 116,
      "title": "",
      "introduced_date": "2019-05-16",
      "latest_action": {
        "date": "2019-05-16",
        "text": "On agreeing to the Harder (CA) amendment (A006) Agreed to by recorded vote: 243 - 174 (Roll no. 211). "
      },
      "policy_area": null
    },
    {
      "id": "hr2696-116",
      "type": "hr",
      "number": "2696",
      "congress": 116,
      "title": "Supporting the Health and Safety of Law Enforcement Act of 2019",
      "introduced_date": "2019-05-14",
      "latest_action": {
        "date": "2019-06-26",
        "text": "Referred to the Subcommittee on Crime, Terrorism, and Homeland Security."
      },
      "policy_area": "Crime and Law Enforcement"
    },
    {
      "id": "hr2697-116",
      "type": "hr",
      "number": "2697",
      "congress": 116,
      "title": "Corporal Ronil Singh and Fallen Heroes Scholarship Act",
      "introduced_date": "2019-05-14",
      "latest_action": {
        "date": "2019-05-14",
        "text": "Referred to the Committee on Education and Labor, and in addition to the Committee on the Budget, for a period to be subsequently determined by the Speaker, in each case for consideration of such provisions as fall within the jurisdiction of the committee concerned."
      },
      "policy_area": "Education"
    },
    {
      "id": "-116",
      "type": "",
      "number": "",
      "congress": 116,
      "title": "",
      "introduced_date": "2019-05-09",
      "latest_action": {
        "date": "2019-05-09",
        "text": "On agreeing to the Harder (CA) amendment (A004) Agreed to by voice vote. "
      },
      "policy_area": null
    },
    {
      "id": "hres361-116",
      "type": "hres",
      "number": "361",
      "congress": 116,
      "title": "Recognizing the importance of paying tribute to those individuals who have faithfully served and retired from the Armed Forces of the United States, supporting the goals and ideals of Military Retiree Appreciation Day, and encouraging the people of the United States to honor the past and continued service of military retirees to their local communities and the United States.",
      "introduced_date": "2019-05-08",
      "latest_action": {
        "date": "2019-05-09",
        "text": "Referred to the Subcommittee on Military Personnel."
      },
      "policy_area": "Armed Forces and National Security"
    },
    {
      "id": "hr2473-116",
      "type": "hr",
      "number": "2473",
      "congress": 116,
      "title": "Securing Access for the central Valley and Enhancing (SAVE) Water Resources Act",
      "introduced_date": "2019-05-02",
      "latest_action": {
        "date": "2020-03-11",
        "text": "Ordered to be Reported (Amended) by the Yeas and Nays: 19 - 12."
      },
      "policy_area": "Water Resources Development"
    }
  ]
}
