{
  "bioguide_id": "M001240",
  "congress": 119,
  "kind": "sponsored",
  "generated_at": "2026-05-07T19:01:17Z",
  "bills": [
    {
      "id": "hres1111-119",
      "type": "hres",
      "number": "1111",
      "congress": 119,
      "title": "Recognizing the 245th anniversary of the Battle of Guilford Courthouse and encouraging all United States citizens to visit the Guilford Courthouse National Military Park in Guilford County, North Carolina.",
      "introduced_date": "2026-03-12",
      "latest_action": {
        "date": "2026-03-12",
        "text": "Referred to the House Committee on Natural Resources."
      },
      "policy_area": "Public Lands and Natural Resources"
    },
    {
      "id": "hr7625-119",
      "type": "hr",
      "number": "7625",
      "congress": 119,
      "title": "MTS CYBER Act of 2026",
      "introduced_date": "2026-02-20",
      "latest_action": {
        "date": "2026-02-20",
        "text": "Referred to the Committee on Transportation and Infrastructure, and in addition to the Committee on Homeland Security, for a period to be subsequently determined by the Speaker, in each case for consideration of such provisions as fall within the jurisdiction of the committee concerned."
      },
      "policy_area": "Transportation and Public Works"
    },
    {
      "id": "hr7184-119",
      "type": "hr",
      "number": "7184",
      "congress": 119,
      "title": "PRESS Act",
      "introduced_date": "2026-01-21",
      "latest_action": {
        "date": "2026-01-21",
        "text": "Referred to the Committee on Energy and Commerce, and in addition to the Committee on the Judiciary, for a period to be subsequently determined by the Speaker, in each case for consideration of such provisions as fall within the jurisdiction of the committee concerned."
      },
      "policy_area": "Crime and Law Enforcement"
    },
    {
      "id": "hr6876-119",
      "type": "hr",
      "number": "6876",
      "congress": 119,
      "title": "Protecting Children from Foreign Mutilation Act",
      "introduced_date": "2025-12-18",
      "latest_action": {
        "date": "2025-12-18",
        "text": "Referred to the House Committee on the Judiciary."
      },
      "policy_area": "Immigration"
    },
    {
      "id": "hr6364-119",
      "type": "hr",
      "number": "6364",
      "congress": 119,
      "title": "Kidd’s Stuttering Act",
      "introduced_date": "2025-12-02",
      "latest_action": {
        "date": "2025-12-02",
        "text": "Referred to the House Committee on Energy and Commerce."
      },
      "policy_area": "Health"
    },
    {
      "id": "hr6152-119",
      "type": "hr",
      "number": "6152",
      "congress": 119,
      "title": "Foreign Robocall Elimination Act",
      "introduced_date": "2025-11-19",
      "latest_action": {
        "date": "2025-11-19",
        "text": "Referred to the House Committee on Energy and Commerce."
      },
      "policy_area": "Science, Technology, Communications"
    },
    {
      "id": "hr5026-119",
      "type": "hr",
      "number": "5026",
      "congress": 119,
      "title": "ALCATRAZ Act",
      "introduced_date": "2025-08-22",
      "latest_action": {
        "date": "2025-08-22",
        "text": "Referred to the Committee on the Judiciary, and in addition to the Committee on Appropriations, for a period to be subsequently determined by the Speaker, in each case for consideration of such provisions as fall within the jurisdiction of the committee concerned."
      },
      "policy_area": "Immigration"
    },
    {
      "id": "hr4411-119",
      "type": "hr",
      "number": "4411",
      "congress": 119,
      "title": "Ban on Inkless Directives and Executive Notarizations Act of 2025",
      "introduced_date": "2025-07-15",
      "latest_action": {
        "date": "2025-07-15",
        "text": "Referred to the House Committee on the Judiciary."
      },
      "policy_area": "Government Operations and Politics"
    },
    {
      "id": "hr4342-119",
      "type": "hr",
      "number": "4342",
      "congress": 119,
      "title": "CURE Act",
      "introduced_date": "2025-07-10",
      "latest_action": {
        "date": "2025-07-10",
        "text": "Referred to the House Committee on Energy and Commerce."
      },
      "policy_area": "Health"
    },
    {
      "id": "hr3725-119",
      "type": "hr",
      "number": "3725",
      "congress": 119,
      "title": "Preventing the Abuse of Immigration Parole Act",
      "introduced_date": "2025-06-04",
      "latest_action": {
        "date": "2025-06-04",
        "text": "Referred to the House Committee on the Judiciary."
      },
      "policy_area": "Immigration"
    },
    {
      "id": "hres447-119",
      "type": "hres",
      "number": "447",
      "congress": 119,
      "title": "Condemning antisemitism and remembering Yaron Lischinsky and Sarah Milgrim.",
      "introduced_date": "2025-05-23",
      "latest_action": {
        "date": "2025-05-23",
        "text": "Referred to the House Committee on the Judiciary."
      },
      "policy_area": "Crime and Law Enforcement"
    },
    {
      "id": "hr2351-119",
      "type": "hr",
      "number": "2351",
      "congress": 119,
      "title": "To direct the Commandant of the Coast Guard to update the policy of the Coast Guard regarding the use of medication to treat drug overdose, and for other purposes.",
      "introduced_date": "2025-03-26",
      "latest_action": {
        "date": "2025-06-10",
        "text": "Received in the Senate and Read twice and referred to the Committee on Commerce, Science, and Transportation."
      },
      "policy_area": "Transportation and Public Works"
    },
    {
      "id": "hr2065-119",
      "type": "hr",
      "number": "2065",
      "congress": 119,
      "title": "Unmasking Hamas Act of 2025",
      "introduced_date": "2025-03-11",
      "latest_action": {
        "date": "2025-03-11",
        "text": "Referred to the House Committee on the Judiciary."
      },
      "policy_area": "Crime and Law Enforcement"
    },
    {
      "id": "hr691-119",
      "type": "hr",
      "number": "691",
      "congress": 119,
      "title": "To designate the Washington Dulles International Airport in Virginia as the \"Donald J. Trump International Airport\".",
      "introduced_date": "2025-01-23",
      "latest_action": {
        "date": "2025-02-01",
        "text": "Referred to the Subcommittee on Aviation."
      },
      "policy_area": "Transportation and Public Works"
    }
  ]
}
